MANIFEST.in
README.md
requirements.txt
setup.py
beachfront/__init__.py
beachfront/coastline.dbf
beachfront/coastline.prj
beachfront/coastline.shp
beachfront/coastline.shx
beachfront/logger.py
beachfront/mask.py
beachfront/process.py
beachfront/vectorize.py
beachfront/version.py
beachfront.egg-info/PKG-INFO
beachfront.egg-info/SOURCES.txt
beachfront.egg-info/dependency_links.txt
beachfront.egg-info/requires.txt
beachfront.egg-info/top_level.txt
test/__init__.py
test/test_logger.py
test/test_mask.py
test/test_process.py
test/test_vectorize.py
test/utils.py