Metadata-Version: 1.1
Name: beachfront
Version: 0.2.3
Summary: library extracting coastline regions from raster data
Home-page: https://github.com/venicegeo/beachfront-py
Author: Matthew Hanson (matthewhanson)
Author-email: UNKNOWN
License: GPL
Platform: UNKNOWN
Classifier: Framework :: Pytest
Classifier: Topic :: Scientific/Engineering :: GIS
Classifier: Topic :: Scientific/Engineering
Classifier: Intended Audience :: Developers
Classifier: Programming Language :: Python :: 2.7
